wyn_agent/__init__.py
wyn_agent/mistral_agent.py
wyn_agent-0.1.9.dist-info/METADATA
wyn_agent-0.1.9.dist-info/WHEEL
wyn_agent-0.1.9.dist-info/RECORD
