Metadata-Version: 2.1
Name: wyn-agent
Version: 0.1.9
Summary: Welcome to the **WYN-Agent** package! This Python package provides a simple yet powerful interface to create AI chatbots using the Mistral AI platform.
Author: Yiqiao Yin
Author-email: eagle0504@gmail.com
Requires-Python: >=3.9,<4.0
Classifier: Programming Language :: Python :: 3
Classifier: Programming Language :: Python :: 3.9
Classifier: Programming Language :: Python :: 3.10
Classifier: Programming Language :: Python :: 3.11
Classifier: Programming Language :: Python :: 3.12
Requires-Dist: mistralai (>=1.0.1,<2.0.0)
